tapioca_senado/__init__.py
tapioca_senado/resource_mapping.py
tapioca_senado/tapioca_senado.py
tapioca_senado-0.5.0.dist-info/LICENSE
tapioca_senado-0.5.0.dist-info/METADATA
tapioca_senado-0.5.0.dist-info/WHEEL
tapioca_senado-0.5.0.dist-info/top_level.txt
tapioca_senado-0.5.0.dist-info/RECORD
