Metadata-Version: 2.1
Name: tapioca-senado
Version: 0.5.0
Summary: API do Senado Federal usando Tapioca
Home-page: https://gitlab.com/maribedran/tapioca-senado
Author: Mariana Bedran Lesche
Author-email: maribedran@gmail.com
License: MIT
Keywords: senado
Platform: UNKNOWN
Classifier: Development Status :: 5 - Production/Stable
Classifier: Intended Audience :: Developers
Classifier: License :: OSI Approved :: MIT License
Classifier: Natural Language :: Portuguese
Classifier: Programming Language :: Python :: 2
Classifier: Programming Language :: Python :: 2.7
Classifier: Programming Language :: Python :: 3
Classifier: Programming Language :: Python :: 3.1
Classifier: Programming Language :: Python :: 3.2
Classifier: Programming Language :: Python :: 3.3
Classifier: Programming Language :: Python :: 3.4
Classifier: Programming Language :: Python :: 3.6
Requires-Dist: tapioca-wrapper (==1.4.2)
